{"Orion Nebula(M42)":{"WWTurl":"http:\/\/tilewall.adlerplanetarium.org:5050\/layerApi.aspx?cmd=mode&lookat=Sky&flyto=-5.3911111111111,5.5881388888889,2.7,0,0","Distance":"1.3 kly","Size":"24 ly","Notes":"The Orion Nebula is a giant stellar nursery. Several hundred stars can be observed in various stages of star formation. (See example of a edge-on proplyd & face-on proplyd.)","Category":"Nebulae","images":["https:\/\/upload.wikimedia.org\/wikipedia\/commons\/4\/45\/Orion_constellation_Hevelius.jpg","https:\/\/upload.wikimedia.org\/wikipedia\/commons\/b\/b0\/Orion_orangefloyd.jpg","https:\/\/upload.wikimedia.org\/wikipedia\/commons\/5\/50\/Ssc2006-16b.jpg"],"wikipedia":"https:\/\/en.wikipedia.org\/wiki\/Orion%27s_Sword"}}